melon/__init__.py
melon/imgreader.py
melon/imgreader_denominations.py
melon/label_format.py
melon/label_generator.py
melon/reader.py
scripts/__init__.py
scripts/cli.py
tests/__init__.py
tests/test_imgreader_no_labels.py
tests/test_imgreader_one_label.py
tests/test_imgreader_sample.py
tests/test_label_generator.py
tests/test_unsupported_files.py
melon-0.1.2.1.dist-info/LICENCE
melon-0.1.2.1.dist-info/METADATA
melon-0.1.2.1.dist-info/WHEEL
melon-0.1.2.1.dist-info/entry_points.txt
melon-0.1.2.1.dist-info/top_level.txt
melon-0.1.2.1.dist-info/RECORD
