Metadata-Version: 2.1
Name: melon
Version: 0.1.2.1
Summary: Lightweight package meant to simplify data processing for Deep Learning
Home-page: https://github.com/romanjoffee/melon
Author: romanjoffee
Author-email: roman.jugai@gmail.com
License: UNKNOWN
Platform: UNKNOWN
Classifier: Programming Language :: Python :: 3
Classifier: License :: OSI Approved :: Apache Software License
Classifier: Operating System :: OS Independent
Requires-Dist: click (==7.0)
Requires-Dist: tqdm (==4.29.0)
Requires-Dist: pillow (==5.4.1)
